mwcliparser/__init__.py
mwcliparser/api.py
mwcliparser/cli.py
mwcliparser-1.0.1.dist-info/LICENSE
mwcliparser-1.0.1.dist-info/METADATA
mwcliparser-1.0.1.dist-info/WHEEL
mwcliparser-1.0.1.dist-info/entry_points.txt
mwcliparser-1.0.1.dist-info/top_level.txt
mwcliparser-1.0.1.dist-info/RECORD
