Metadata-Version: 2.1
Name: mwcliparser
Version: 1.0.1
Summary: Merrian-Webster command line utility to get word definition.
Author-email: Vikash Kumar Shrivastva <vkshrivastva@yahoo.co.in>
Maintainer-email: Vikash Kumar Shrivastva <vkshrivastva@yahoo.co.in>
License: Copyright (c) 2018 The Python Packaging Authority
Requires-Python: >=3.8
License-File: LICENSE
